odoo/addons/stock_valuation_layer_usage/README.rst
odoo/addons/stock_valuation_layer_usage/__init__.py
odoo/addons/stock_valuation_layer_usage/__manifest__.py
odoo/addons/stock_valuation_layer_usage/i18n/es.po
odoo/addons/stock_valuation_layer_usage/i18n/it.po
odoo/addons/stock_valuation_layer_usage/i18n/pt.po
odoo/addons/stock_valuation_layer_usage/i18n/pt_BR.po
odoo/addons/stock_valuation_layer_usage/i18n/stock_valuation_layer_usage.pot
odoo/addons/stock_valuation_layer_usage/models/__init__.py
odoo/addons/stock_valuation_layer_usage/models/stock_move.py
odoo/addons/stock_valuation_layer_usage/models/stock_valuation_layer.py
odoo/addons/stock_valuation_layer_usage/models/stock_valuation_layer_usage.py
odoo/addons/stock_valuation_layer_usage/readme/CONTRIBUTORS.md
odoo/addons/stock_valuation_layer_usage/readme/DESCRIPTION.md
odoo/addons/stock_valuation_layer_usage/readme/HISTORY.md
odoo/addons/stock_valuation_layer_usage/readme/INSTALL.md
odoo/addons/stock_valuation_layer_usage/readme/USAGE.md
odoo/addons/stock_valuation_layer_usage/security/ir.model.access.csv
odoo/addons/stock_valuation_layer_usage/security/ir_rule.xml
odoo/addons/stock_valuation_layer_usage/static/description/icon.png
odoo/addons/stock_valuation_layer_usage/static/description/index.html
odoo/addons/stock_valuation_layer_usage/tests/__init__.py
odoo/addons/stock_valuation_layer_usage/tests/test_stock_valuation_layer_usage.py
odoo/addons/stock_valuation_layer_usage/views/stock_move_views.xml
odoo/addons/stock_valuation_layer_usage/views/stock_valuation_layer_usage_views.xml
odoo/addons/stock_valuation_layer_usage/views/stock_valuation_layer_views.xml
odoo_addon_stock_valuation_layer_usage-18.0.1.0.0.4.dist-info/METADATA
odoo_addon_stock_valuation_layer_usage-18.0.1.0.0.4.dist-info/WHEEL
odoo_addon_stock_valuation_layer_usage-18.0.1.0.0.4.dist-info/top_level.txt
odoo_addon_stock_valuation_layer_usage-18.0.1.0.0.4.dist-info/RECORD
