Metadata-Version: 2.1
Name: odoo-addon-stock_valuation_layer_usage
Version: 18.0.1.0.0.4
Requires-Python: >=3.10
Requires-Dist: odoo-addon-stock_account_product_run_fifo_hook==18.0.*
Requires-Dist: odoo==18.0.*
Summary: Trace where has the stock valuation been used in, including the quantities taken.
Home-page: https://github.com/OCA/stock-logistics-workflow
License: AGPL-3
Author: ForgeFlow,Odoo Community Association (OCA)
Author-email: support@odoo-community.org
Classifier: Programming Language :: Python
Classifier: Framework :: Odoo
Classifier: Framework :: Odoo :: 18.0
Classifier: License :: OSI Approved :: GNU Affero General Public License v3
Classifier: Development Status :: 3 - Alpha
